{"nodes": [{"id": "d_replit_projects_new_2_portfolio_fixer_artifacts_admin_src_pages_messagesmanager_tsx", "label": "MessagesManager.tsx", "file_type": "code", "source_file": "D:\\replit_projects\\new_2\\Portfolio-Fixer\\artifacts\\admin\\src\\pages\\MessagesManager.tsx", "source_location": "L1"}, {"id": "pages_messagesmanager_msgstatus", "label": "MsgStatus", "file_type": "code", "source_file": "D:\\replit_projects\\new_2\\Portfolio-Fixer\\artifacts\\admin\\src\\pages\\MessagesManager.tsx", "source_location": "L24"}, {"id": "pages_messagesmanager_msg", "label": "Msg", "file_type": "code", "source_file": "D:\\replit_projects\\new_2\\Portfolio-Fixer\\artifacts\\admin\\src\\pages\\MessagesManager.tsx", "source_location": "L25"}, {"id": "pages_messagesmanager_isunread", "label": "isUnread()", "file_type": "code", "source_file": "D:\\replit_projects\\new_2\\Portfolio-Fixer\\artifacts\\admin\\src\\pages\\MessagesManager.tsx", "source_location": "L34"}, {"id": "pages_messagesmanager_isarchived", "label": "isArchived()", "file_type": "code", "source_file": "D:\\replit_projects\\new_2\\Portfolio-Fixer\\artifacts\\admin\\src\\pages\\MessagesManager.tsx", "source_location": "L38"}, {"id": "pages_messagesmanager_status_filters", "label": "STATUS_FILTERS", "file_type": "code", "source_file": "D:\\replit_projects\\new_2\\Portfolio-Fixer\\artifacts\\admin\\src\\pages\\MessagesManager.tsx", "source_location": "L42"}, {"id": "pages_messagesmanager_messagesuiprops", "label": "MessagesUIProps", "file_type": "code", "source_file": "D:\\replit_projects\\new_2\\Portfolio-Fixer\\artifacts\\admin\\src\\pages\\MessagesManager.tsx", "source_location": "L53"}, {"id": "pages_messagesmanager_messagesui", "label": "MessagesUI()", "file_type": "code", "source_file": "D:\\replit_projects\\new_2\\Portfolio-Fixer\\artifacts\\admin\\src\\pages\\MessagesManager.tsx", "source_location": "L78"}, {"id": "pages_messagesmanager_messagesmanager", "label": "MessagesManager()", "file_type": "code", "source_file": "D:\\replit_projects\\new_2\\Portfolio-Fixer\\artifacts\\admin\\src\\pages\\MessagesManager.tsx", "source_location": "L338"}], "edges": [{"source": "d_replit_projects_new_2_portfolio_fixer_artifacts_admin_src_pages_messagesmanager_tsx", "target": "react_query", "relation": "imports_from", "context": "import", "confidence": "EXTRACTED", "source_file": "D:\\replit_projects\\new_2\\Portfolio-Fixer\\artifacts\\admin\\src\\pages\\MessagesManager.tsx", "source_location": "L1", "weight": 1.0}, {"source": "d_replit_projects_new_2_portfolio_fixer_artifacts_admin_src_pages_messagesmanager_tsx", "target": "react", "relation": "imports_from", "context": "import", "confidence": "EXTRACTED", "source_file": "D:\\replit_projects\\new_2\\Portfolio-Fixer\\artifacts\\admin\\src\\pages\\MessagesManager.tsx", "source_location": "L2", "weight": 1.0}, {"source": "d_replit_projects_new_2_portfolio_fixer_artifacts_admin_src_pages_messagesmanager_tsx", "target": "ui", "relation": "imports_from", "context": "import", "confidence": "EXTRACTED", "source_file": "D:\\replit_projects\\new_2\\Portfolio-Fixer\\artifacts\\admin\\src\\pages\\MessagesManager.tsx", "source_location": "L3", "weight": 1.0}, {"source": "d_replit_projects_new_2_portfolio_fixer_artifacts_admin_src_pages_messagesmanager_tsx", "target": "ui", "relation": "imports_from", "context": "import", "confidence": "EXTRACTED", "source_file": "D:\\replit_projects\\new_2\\Portfolio-Fixer\\artifacts\\admin\\src\\pages\\MessagesManager.tsx", "source_location": "L4", "weight": 1.0}, {"source": "d_replit_projects_new_2_portfolio_fixer_artifacts_admin_src_pages_messagesmanager_tsx", "target": "lucide_react", "relation": "imports_from", "context": "import", "confidence": "EXTRACTED", "source_file": "D:\\replit_projects\\new_2\\Portfolio-Fixer\\artifacts\\admin\\src\\pages\\MessagesManager.tsx", "source_location": "L5", "weight": 1.0}, {"source": "d_replit_projects_new_2_portfolio_fixer_artifacts_admin_src_pages_messagesmanager_tsx", "target": "d_replit_projects_new_2_portfolio_fixer_artifacts_admin_src_lib_api_client_ts", "relation": "imports_from", "context": "import", "confidence": "EXTRACTED", "source_file": "D:\\replit_projects\\new_2\\Portfolio-Fixer\\artifacts\\admin\\src\\pages\\MessagesManager.tsx", "source_location": "L16", "weight": 1.0}, {"source": "d_replit_projects_new_2_portfolio_fixer_artifacts_admin_src_pages_messagesmanager_tsx", "target": "lib_api_client_api", "relation": "imports", "context": "import", "confidence": "EXTRACTED", "source_file": "D:\\replit_projects\\new_2\\Portfolio-Fixer\\artifacts\\admin\\src\\pages\\MessagesManager.tsx", "source_location": "L16", "weight": 1.0}, {"source": "d_replit_projects_new_2_portfolio_fixer_artifacts_admin_src_pages_messagesmanager_tsx", "target": "ui", "relation": "imports_from", "context": "import", "confidence": "EXTRACTED", "source_file": "D:\\replit_projects\\new_2\\Portfolio-Fixer\\artifacts\\admin\\src\\pages\\MessagesManager.tsx", "source_location": "L17", "weight": 1.0}, {"source": "d_replit_projects_new_2_portfolio_fixer_artifacts_admin_src_pages_messagesmanager_tsx", "target": "d_replit_projects_new_2_portfolio_fixer_artifacts_admin_src_components_smartconfirmdialog_tsx", "relation": "imports_from", "context": "import", "confidence": "EXTRACTED", "source_file": "D:\\replit_projects\\new_2\\Portfolio-Fixer\\artifacts\\admin\\src\\pages\\MessagesManager.tsx", "source_location": "L18", "weight": 1.0}, {"source": "d_replit_projects_new_2_portfolio_fixer_artifacts_admin_src_pages_messagesmanager_tsx", "target": "components_smartconfirmdialog_smartconfirmdialog", "relation": "imports", "context": "import", "confidence": "EXTRACTED", "source_file": "D:\\replit_projects\\new_2\\Portfolio-Fixer\\artifacts\\admin\\src\\pages\\MessagesManager.tsx", "source_location": "L18", "weight": 1.0}, {"source": "d_replit_projects_new_2_portfolio_fixer_artifacts_admin_src_pages_messagesmanager_tsx", "target": "d_replit_projects_new_2_portfolio_fixer_artifacts_admin_src_components_smartemptystate_tsx", "relation": "imports_from", "context": "import", "confidence": "EXTRACTED", "source_file": "D:\\replit_projects\\new_2\\Portfolio-Fixer\\artifacts\\admin\\src\\pages\\MessagesManager.tsx", "source_location": "L19", "weight": 1.0}, {"source": "d_replit_projects_new_2_portfolio_fixer_artifacts_admin_src_pages_messagesmanager_tsx", "target": "components_smartemptystate_smartemptystate", "relation": "imports", "context": "import", "confidence": "EXTRACTED", "source_file": "D:\\replit_projects\\new_2\\Portfolio-Fixer\\artifacts\\admin\\src\\pages\\MessagesManager.tsx", "source_location": "L19", "weight": 1.0}, {"source": "d_replit_projects_new_2_portfolio_fixer_artifacts_admin_src_pages_messagesmanager_tsx", "target": "d_replit_projects_new_2_portfolio_fixer_artifacts_admin_src_lib_error_messages_ts", "relation": "imports_from", "context": "import", "confidence": "EXTRACTED", "source_file": "D:\\replit_projects\\new_2\\Portfolio-Fixer\\artifacts\\admin\\src\\pages\\MessagesManager.tsx", "source_location": "L20", "weight": 1.0}, {"source": "d_replit_projects_new_2_portfolio_fixer_artifacts_admin_src_pages_messagesmanager_tsx", "target": "lib_error_messages_geterrormessage", "relation": "imports", "context": "import", "confidence": "EXTRACTED", "source_file": "D:\\replit_projects\\new_2\\Portfolio-Fixer\\artifacts\\admin\\src\\pages\\MessagesManager.tsx", "source_location": "L20", "weight": 1.0}, {"source": "d_replit_projects_new_2_portfolio_fixer_artifacts_admin_src_pages_messagesmanager_tsx", "target": "pages_messagesmanager_msgstatus", "relation": "contains", "confidence": "EXTRACTED", "source_file": "D:\\replit_projects\\new_2\\Portfolio-Fixer\\artifacts\\admin\\src\\pages\\MessagesManager.tsx", "source_location": "L24", "weight": 1.0}, {"source": "d_replit_projects_new_2_portfolio_fixer_artifacts_admin_src_pages_messagesmanager_tsx", "target": "pages_messagesmanager_msg", "relation": "contains", "confidence": "EXTRACTED", "source_file": "D:\\replit_projects\\new_2\\Portfolio-Fixer\\artifacts\\admin\\src\\pages\\MessagesManager.tsx", "source_location": "L25", "weight": 1.0}, {"source": "d_replit_projects_new_2_portfolio_fixer_artifacts_admin_src_pages_messagesmanager_tsx", "target": "pages_messagesmanager_isunread", "relation": "contains", "confidence": "EXTRACTED", "source_file": "D:\\replit_projects\\new_2\\Portfolio-Fixer\\artifacts\\admin\\src\\pages\\MessagesManager.tsx", "source_location": "L34", "weight": 1.0}, {"source": "d_replit_projects_new_2_portfolio_fixer_artifacts_admin_src_pages_messagesmanager_tsx", "target": "pages_messagesmanager_isarchived", "relation": "contains", "confidence": "EXTRACTED", "source_file": "D:\\replit_projects\\new_2\\Portfolio-Fixer\\artifacts\\admin\\src\\pages\\MessagesManager.tsx", "source_location": "L38", "weight": 1.0}, {"source": "d_replit_projects_new_2_portfolio_fixer_artifacts_admin_src_pages_messagesmanager_tsx", "target": "pages_messagesmanager_status_filters", "relation": "contains", "confidence": "EXTRACTED", "source_file": "D:\\replit_projects\\new_2\\Portfolio-Fixer\\artifacts\\admin\\src\\pages\\MessagesManager.tsx", "source_location": "L42", "weight": 1.0}, {"source": "d_replit_projects_new_2_portfolio_fixer_artifacts_admin_src_pages_messagesmanager_tsx", "target": "pages_messagesmanager_messagesuiprops", "relation": "contains", "confidence": "EXTRACTED", "source_file": "D:\\replit_projects\\new_2\\Portfolio-Fixer\\artifacts\\admin\\src\\pages\\MessagesManager.tsx", "source_location": "L53", "weight": 1.0}, {"source": "d_replit_projects_new_2_portfolio_fixer_artifacts_admin_src_pages_messagesmanager_tsx", "target": "pages_messagesmanager_messagesui", "relation": "contains", "confidence": "EXTRACTED", "source_file": "D:\\replit_projects\\new_2\\Portfolio-Fixer\\artifacts\\admin\\src\\pages\\MessagesManager.tsx", "source_location": "L78", "weight": 1.0}, {"source": "d_replit_projects_new_2_portfolio_fixer_artifacts_admin_src_pages_messagesmanager_tsx", "target": "pages_messagesmanager_messagesmanager", "relation": "contains", "confidence": "EXTRACTED", "source_file": "D:\\replit_projects\\new_2\\Portfolio-Fixer\\artifacts\\admin\\src\\pages\\MessagesManager.tsx", "source_location": "L338", "weight": 1.0}], "raw_calls": [{"caller_nid": "pages_messagesmanager_messagesui", "callee": "map", "is_member_call": true, "source_file": "D:\\replit_projects\\new_2\\Portfolio-Fixer\\artifacts\\admin\\src\\pages\\MessagesManager.tsx", "source_location": "L124"}, {"caller_nid": "pages_messagesmanager_messagesui", "callee": "map", "is_member_call": true, "source_file": "D:\\replit_projects\\new_2\\Portfolio-Fixer\\artifacts\\admin\\src\\pages\\MessagesManager.tsx", "source_location": "L171"}, {"caller_nid": "pages_messagesmanager_messagesui", "callee": "min", "is_member_call": true, "source_file": "D:\\replit_projects\\new_2\\Portfolio-Fixer\\artifacts\\admin\\src\\pages\\MessagesManager.tsx", "source_location": "L262"}, {"caller_nid": "pages_messagesmanager_messagesui", "callee": "String", "is_member_call": false, "source_file": "D:\\replit_projects\\new_2\\Portfolio-Fixer\\artifacts\\admin\\src\\pages\\MessagesManager.tsx", "source_location": "L264"}, {"caller_nid": "pages_messagesmanager_messagesui", "callee": "ceil", "is_member_call": true, "source_file": "D:\\replit_projects\\new_2\\Portfolio-Fixer\\artifacts\\admin\\src\\pages\\MessagesManager.tsx", "source_location": "L279"}, {"caller_nid": "pages_messagesmanager_messagesmanager", "callee": "useToast", "is_member_call": false, "source_file": "D:\\replit_projects\\new_2\\Portfolio-Fixer\\artifacts\\admin\\src\\pages\\MessagesManager.tsx", "source_location": "L339"}, {"caller_nid": "pages_messagesmanager_messagesmanager", "callee": "useQuery", "is_member_call": false, "source_file": "D:\\replit_projects\\new_2\\Portfolio-Fixer\\artifacts\\admin\\src\\pages\\MessagesManager.tsx", "source_location": "L340"}, {"caller_nid": "pages_messagesmanager_messagesmanager", "callee": "useState", "is_member_call": false, "source_file": "D:\\replit_projects\\new_2\\Portfolio-Fixer\\artifacts\\admin\\src\\pages\\MessagesManager.tsx", "source_location": "L349"}, {"caller_nid": "pages_messagesmanager_messagesmanager", "callee": "useState", "is_member_call": false, "source_file": "D:\\replit_projects\\new_2\\Portfolio-Fixer\\artifacts\\admin\\src\\pages\\MessagesManager.tsx", "source_location": "L350"}, {"caller_nid": "pages_messagesmanager_messagesmanager", "callee": "useState", "is_member_call": false, "source_file": "D:\\replit_projects\\new_2\\Portfolio-Fixer\\artifacts\\admin\\src\\pages\\MessagesManager.tsx", "source_location": "L351"}, {"caller_nid": "pages_messagesmanager_messagesmanager", "callee": "useState", "is_member_call": false, "source_file": "D:\\replit_projects\\new_2\\Portfolio-Fixer\\artifacts\\admin\\src\\pages\\MessagesManager.tsx", "source_location": "L352"}, {"caller_nid": "pages_messagesmanager_messagesmanager", "callee": "useState", "is_member_call": false, "source_file": "D:\\replit_projects\\new_2\\Portfolio-Fixer\\artifacts\\admin\\src\\pages\\MessagesManager.tsx", "source_location": "L353"}, {"caller_nid": "pages_messagesmanager_messagesmanager", "callee": "useState", "is_member_call": false, "source_file": "D:\\replit_projects\\new_2\\Portfolio-Fixer\\artifacts\\admin\\src\\pages\\MessagesManager.tsx", "source_location": "L354"}, {"caller_nid": "pages_messagesmanager_messagesmanager", "callee": "useState", "is_member_call": false, "source_file": "D:\\replit_projects\\new_2\\Portfolio-Fixer\\artifacts\\admin\\src\\pages\\MessagesManager.tsx", "source_location": "L355"}, {"caller_nid": "pages_messagesmanager_messagesmanager", "callee": "useMemo", "is_member_call": false, "source_file": "D:\\replit_projects\\new_2\\Portfolio-Fixer\\artifacts\\admin\\src\\pages\\MessagesManager.tsx", "source_location": "L357"}, {"caller_nid": "pages_messagesmanager_messagesmanager", "callee": "useMemo", "is_member_call": false, "source_file": "D:\\replit_projects\\new_2\\Portfolio-Fixer\\artifacts\\admin\\src\\pages\\MessagesManager.tsx", "source_location": "L362"}, {"caller_nid": "pages_messagesmanager_messagesmanager", "callee": "useMemo", "is_member_call": false, "source_file": "D:\\replit_projects\\new_2\\Portfolio-Fixer\\artifacts\\admin\\src\\pages\\MessagesManager.tsx", "source_location": "L373"}, {"caller_nid": "pages_messagesmanager_messagesmanager", "callee": "map", "is_member_call": true, "source_file": "D:\\replit_projects\\new_2\\Portfolio-Fixer\\artifacts\\admin\\src\\pages\\MessagesManager.tsx", "source_location": "L409"}, {"caller_nid": "pages_messagesmanager_messagesmanager", "callee": "getErrorMessage", "is_member_call": false, "source_file": "D:\\replit_projects\\new_2\\Portfolio-Fixer\\artifacts\\admin\\src\\pages\\MessagesManager.tsx", "source_location": "L421"}]}