{"nodes": [{"id": "d_replit_projects_new_2_portfolio_fixer_lib_db_src_storage_ts", "label": "storage.ts", "file_type": "code", "source_file": "D:\\replit_projects\\new_2\\Portfolio-Fixer\\lib\\db\\src\\storage.ts", "source_location": "L1"}, {"id": "src_storage_supabase_url", "label": "SUPABASE_URL", "file_type": "code", "source_file": "D:\\replit_projects\\new_2\\Portfolio-Fixer\\lib\\db\\src\\storage.ts", "source_location": "L3"}, {"id": "src_storage_bucketname", "label": "BucketName", "file_type": "code", "source_file": "D:\\replit_projects\\new_2\\Portfolio-Fixer\\lib\\db\\src\\storage.ts", "source_location": "L5"}, {"id": "src_storage_uploadresult", "label": "UploadResult", "file_type": "code", "source_file": "D:\\replit_projects\\new_2\\Portfolio-Fixer\\lib\\db\\src\\storage.ts", "source_location": "L7"}, {"id": "src_storage_sanitizefilename", "label": "sanitizeFilename()", "file_type": "code", "source_file": "D:\\replit_projects\\new_2\\Portfolio-Fixer\\lib\\db\\src\\storage.ts", "source_location": "L11"}, {"id": "src_storage_issupabasestorageurl", "label": "isSupabaseStorageUrl()", "file_type": "code", "source_file": "D:\\replit_projects\\new_2\\Portfolio-Fixer\\lib\\db\\src\\storage.ts", "source_location": "L21"}, {"id": "src_storage_extractstoragepath", "label": "extractStoragePath()", "file_type": "code", "source_file": "D:\\replit_projects\\new_2\\Portfolio-Fixer\\lib\\db\\src\\storage.ts", "source_location": "L27"}, {"id": "src_storage_uploadfile", "label": "uploadFile()", "file_type": "code", "source_file": "D:\\replit_projects\\new_2\\Portfolio-Fixer\\lib\\db\\src\\storage.ts", "source_location": "L34"}, {"id": "src_storage_deletefile", "label": "deleteFile()", "file_type": "code", "source_file": "D:\\replit_projects\\new_2\\Portfolio-Fixer\\lib\\db\\src\\storage.ts", "source_location": "L66"}, {"id": "src_storage_getpublicurl", "label": "getPublicUrl()", "file_type": "code", "source_file": "D:\\replit_projects\\new_2\\Portfolio-Fixer\\lib\\db\\src\\storage.ts", "source_location": "L81"}, {"id": "src_storage_uploadfilewithprogress", "label": "uploadFileWithProgress()", "file_type": "code", "source_file": "D:\\replit_projects\\new_2\\Portfolio-Fixer\\lib\\db\\src\\storage.ts", "source_location": "L90"}], "edges": [{"source": "d_replit_projects_new_2_portfolio_fixer_lib_db_src_storage_ts", "target": "client", "relation": "imports_from", "context": "import", "confidence": "EXTRACTED", "source_file": "D:\\replit_projects\\new_2\\Portfolio-Fixer\\lib\\db\\src\\storage.ts", "source_location": "L1", "weight": 1.0}, {"source": "d_replit_projects_new_2_portfolio_fixer_lib_db_src_storage_ts", "target": "src_storage_supabase_url", "relation": "contains", "confidence": "EXTRACTED", "source_file": "D:\\replit_projects\\new_2\\Portfolio-Fixer\\lib\\db\\src\\storage.ts", "source_location": "L3", "weight": 1.0}, {"source": "d_replit_projects_new_2_portfolio_fixer_lib_db_src_storage_ts", "target": "src_storage_bucketname", "relation": "contains", "confidence": "EXTRACTED", "source_file": "D:\\replit_projects\\new_2\\Portfolio-Fixer\\lib\\db\\src\\storage.ts", "source_location": "L5", "weight": 1.0}, {"source": "d_replit_projects_new_2_portfolio_fixer_lib_db_src_storage_ts", "target": "src_storage_uploadresult", "relation": "contains", "confidence": "EXTRACTED", "source_file": "D:\\replit_projects\\new_2\\Portfolio-Fixer\\lib\\db\\src\\storage.ts", "source_location": "L7", "weight": 1.0}, {"source": "d_replit_projects_new_2_portfolio_fixer_lib_db_src_storage_ts", "target": "src_storage_sanitizefilename", "relation": "contains", "confidence": "EXTRACTED", "source_file": "D:\\replit_projects\\new_2\\Portfolio-Fixer\\lib\\db\\src\\storage.ts", "source_location": "L11", "weight": 1.0}, {"source": "d_replit_projects_new_2_portfolio_fixer_lib_db_src_storage_ts", "target": "src_storage_issupabasestorageurl", "relation": "contains", "confidence": "EXTRACTED", "source_file": "D:\\replit_projects\\new_2\\Portfolio-Fixer\\lib\\db\\src\\storage.ts", "source_location": "L21", "weight": 1.0}, {"source": "d_replit_projects_new_2_portfolio_fixer_lib_db_src_storage_ts", "target": "src_storage_extractstoragepath", "relation": "contains", "confidence": "EXTRACTED", "source_file": "D:\\replit_projects\\new_2\\Portfolio-Fixer\\lib\\db\\src\\storage.ts", "source_location": "L27", "weight": 1.0}, {"source": "d_replit_projects_new_2_portfolio_fixer_lib_db_src_storage_ts", "target": "src_storage_uploadfile", "relation": "contains", "confidence": "EXTRACTED", "source_file": "D:\\replit_projects\\new_2\\Portfolio-Fixer\\lib\\db\\src\\storage.ts", "source_location": "L34", "weight": 1.0}, {"source": "d_replit_projects_new_2_portfolio_fixer_lib_db_src_storage_ts", "target": "src_storage_deletefile", "relation": "contains", "confidence": "EXTRACTED", "source_file": "D:\\replit_projects\\new_2\\Portfolio-Fixer\\lib\\db\\src\\storage.ts", "source_location": "L66", "weight": 1.0}, {"source": "d_replit_projects_new_2_portfolio_fixer_lib_db_src_storage_ts", "target": "src_storage_getpublicurl", "relation": "contains", "confidence": "EXTRACTED", "source_file": "D:\\replit_projects\\new_2\\Portfolio-Fixer\\lib\\db\\src\\storage.ts", "source_location": "L81", "weight": 1.0}, {"source": "d_replit_projects_new_2_portfolio_fixer_lib_db_src_storage_ts", "target": "src_storage_uploadfilewithprogress", "relation": "contains", "confidence": "EXTRACTED", "source_file": "D:\\replit_projects\\new_2\\Portfolio-Fixer\\lib\\db\\src\\storage.ts", "source_location": "L90", "weight": 1.0}, {"source": "src_storage_uploadfile", "target": "src_storage_sanitizefilename", "relation": "calls", "context": "call", "confidence": "EXTRACTED", "source_file": "D:\\replit_projects\\new_2\\Portfolio-Fixer\\lib\\db\\src\\storage.ts", "source_location": "L40", "weight": 1.0}, {"source": "src_storage_uploadfile", "target": "src_storage_getpublicurl", "relation": "calls", "context": "call", "confidence": "EXTRACTED", "source_file": "D:\\replit_projects\\new_2\\Portfolio-Fixer\\lib\\db\\src\\storage.ts", "source_location": "L56", "weight": 1.0}, {"source": "src_storage_uploadfilewithprogress", "target": "src_storage_sanitizefilename", "relation": "calls", "context": "call", "confidence": "EXTRACTED", "source_file": "D:\\replit_projects\\new_2\\Portfolio-Fixer\\lib\\db\\src\\storage.ts", "source_location": "L97", "weight": 1.0}], "raw_calls": [{"caller_nid": "src_storage_sanitizefilename", "callee": "replace", "is_member_call": true, "source_file": "D:\\replit_projects\\new_2\\Portfolio-Fixer\\lib\\db\\src\\storage.ts", "source_location": "L12"}, {"caller_nid": "src_storage_sanitizefilename", "callee": "replace", "is_member_call": true, "source_file": "D:\\replit_projects\\new_2\\Portfolio-Fixer\\lib\\db\\src\\storage.ts", "source_location": "L12"}, {"caller_nid": "src_storage_sanitizefilename", "callee": "replace", "is_member_call": true, "source_file": "D:\\replit_projects\\new_2\\Portfolio-Fixer\\lib\\db\\src\\storage.ts", "source_location": "L12"}, {"caller_nid": "src_storage_sanitizefilename", "callee": "replace", "is_member_call": true, "source_file": "D:\\replit_projects\\new_2\\Portfolio-Fixer\\lib\\db\\src\\storage.ts", "source_location": "L12"}, {"caller_nid": "src_storage_sanitizefilename", "callee": "replace", "is_member_call": true, "source_file": "D:\\replit_projects\\new_2\\Portfolio-Fixer\\lib\\db\\src\\storage.ts", "source_location": "L12"}, {"caller_nid": "src_storage_sanitizefilename", "callee": "toLowerCase", "is_member_call": true, "source_file": "D:\\replit_projects\\new_2\\Portfolio-Fixer\\lib\\db\\src\\storage.ts", "source_location": "L12"}, {"caller_nid": "src_storage_issupabasestorageurl", "callee": "startsWith", "is_member_call": true, "source_file": "D:\\replit_projects\\new_2\\Portfolio-Fixer\\lib\\db\\src\\storage.ts", "source_location": "L24"}, {"caller_nid": "src_storage_extractstoragepath", "callee": "startsWith", "is_member_call": true, "source_file": "D:\\replit_projects\\new_2\\Portfolio-Fixer\\lib\\db\\src\\storage.ts", "source_location": "L30"}, {"caller_nid": "src_storage_extractstoragepath", "callee": "slice", "is_member_call": true, "source_file": "D:\\replit_projects\\new_2\\Portfolio-Fixer\\lib\\db\\src\\storage.ts", "source_location": "L31"}, {"caller_nid": "src_storage_uploadfile", "callee": "getSupabase", "is_member_call": false, "source_file": "D:\\replit_projects\\new_2\\Portfolio-Fixer\\lib\\db\\src\\storage.ts", "source_location": "L39"}, {"caller_nid": "src_storage_uploadfile", "callee": "now", "is_member_call": true, "source_file": "D:\\replit_projects\\new_2\\Portfolio-Fixer\\lib\\db\\src\\storage.ts", "source_location": "L41"}, {"caller_nid": "src_storage_uploadfile", "callee": "upload", "is_member_call": true, "source_file": "D:\\replit_projects\\new_2\\Portfolio-Fixer\\lib\\db\\src\\storage.ts", "source_location": "L45"}, {"caller_nid": "src_storage_uploadfile", "callee": "from", "is_member_call": true, "source_file": "D:\\replit_projects\\new_2\\Portfolio-Fixer\\lib\\db\\src\\storage.ts", "source_location": "L45"}, {"caller_nid": "src_storage_uploadfile", "callee": "from", "is_member_call": true, "source_file": "D:\\replit_projects\\new_2\\Portfolio-Fixer\\lib\\db\\src\\storage.ts", "source_location": "L56"}, {"caller_nid": "src_storage_deletefile", "callee": "getSupabase", "is_member_call": false, "source_file": "D:\\replit_projects\\new_2\\Portfolio-Fixer\\lib\\db\\src\\storage.ts", "source_location": "L70"}, {"caller_nid": "src_storage_deletefile", "callee": "remove", "is_member_call": true, "source_file": "D:\\replit_projects\\new_2\\Portfolio-Fixer\\lib\\db\\src\\storage.ts", "source_location": "L72"}, {"caller_nid": "src_storage_deletefile", "callee": "from", "is_member_call": true, "source_file": "D:\\replit_projects\\new_2\\Portfolio-Fixer\\lib\\db\\src\\storage.ts", "source_location": "L72"}, {"caller_nid": "src_storage_getpublicurl", "callee": "getSupabase", "is_member_call": false, "source_file": "D:\\replit_projects\\new_2\\Portfolio-Fixer\\lib\\db\\src\\storage.ts", "source_location": "L85"}, {"caller_nid": "src_storage_getpublicurl", "callee": "from", "is_member_call": true, "source_file": "D:\\replit_projects\\new_2\\Portfolio-Fixer\\lib\\db\\src\\storage.ts", "source_location": "L86"}, {"caller_nid": "src_storage_uploadfilewithprogress", "callee": "getSupabase", "is_member_call": false, "source_file": "D:\\replit_projects\\new_2\\Portfolio-Fixer\\lib\\db\\src\\storage.ts", "source_location": "L96"}, {"caller_nid": "src_storage_uploadfilewithprogress", "callee": "now", "is_member_call": true, "source_file": "D:\\replit_projects\\new_2\\Portfolio-Fixer\\lib\\db\\src\\storage.ts", "source_location": "L98"}]}