{"nodes": [{"id": "d_replit_projects_new_2_portfolio_fixer_artifacts_admin_src_pages_abouteditor_tsx", "label": "AboutEditor.tsx", "file_type": "code", "source_file": "D:\\replit_projects\\new_2\\Portfolio-Fixer\\artifacts\\admin\\src\\pages\\AboutEditor.tsx", "source_location": "L1"}, {"id": "pages_abouteditor_aboutformdata", "label": "AboutFormData", "file_type": "code", "source_file": "D:\\replit_projects\\new_2\\Portfolio-Fixer\\artifacts\\admin\\src\\pages\\AboutEditor.tsx", "source_location": "L11"}, {"id": "pages_abouteditor_skeletonform", "label": "SkeletonForm()", "file_type": "code", "source_file": "D:\\replit_projects\\new_2\\Portfolio-Fixer\\artifacts\\admin\\src\\pages\\AboutEditor.tsx", "source_location": "L26"}, {"id": "pages_abouteditor_skeletonpreview", "label": "SkeletonPreview()", "file_type": "code", "source_file": "D:\\replit_projects\\new_2\\Portfolio-Fixer\\artifacts\\admin\\src\\pages\\AboutEditor.tsx", "source_location": "L45"}, {"id": "pages_abouteditor_getlanguagelabel", "label": "getLanguageLabel()", "file_type": "code", "source_file": "D:\\replit_projects\\new_2\\Portfolio-Fixer\\artifacts\\admin\\src\\pages\\AboutEditor.tsx", "source_location": "L53"}, {"id": "pages_abouteditor_livepreviewdata", "label": "LivePreviewData", "file_type": "code", "source_file": "D:\\replit_projects\\new_2\\Portfolio-Fixer\\artifacts\\admin\\src\\pages\\AboutEditor.tsx", "source_location": "L61"}, {"id": "pages_abouteditor_livepreview", "label": "LivePreview()", "file_type": "code", "source_file": "D:\\replit_projects\\new_2\\Portfolio-Fixer\\artifacts\\admin\\src\\pages\\AboutEditor.tsx", "source_location": "L76"}, {"id": "pages_abouteditor_abouteditor", "label": "AboutEditor()", "file_type": "code", "source_file": "D:\\replit_projects\\new_2\\Portfolio-Fixer\\artifacts\\admin\\src\\pages\\AboutEditor.tsx", "source_location": "L156"}], "edges": [{"source": "d_replit_projects_new_2_portfolio_fixer_artifacts_admin_src_pages_abouteditor_tsx", "target": "react", "relation": "imports_from", "context": "import", "confidence": "EXTRACTED", "source_file": "D:\\replit_projects\\new_2\\Portfolio-Fixer\\artifacts\\admin\\src\\pages\\AboutEditor.tsx", "source_location": "L1", "weight": 1.0}, {"source": "d_replit_projects_new_2_portfolio_fixer_artifacts_admin_src_pages_abouteditor_tsx", "target": "react_query", "relation": "imports_from", "context": "import", "confidence": "EXTRACTED", "source_file": "D:\\replit_projects\\new_2\\Portfolio-Fixer\\artifacts\\admin\\src\\pages\\AboutEditor.tsx", "source_location": "L2", "weight": 1.0}, {"source": "d_replit_projects_new_2_portfolio_fixer_artifacts_admin_src_pages_abouteditor_tsx", "target": "react_hook_form", "relation": "imports_from", "context": "import", "confidence": "EXTRACTED", "source_file": "D:\\replit_projects\\new_2\\Portfolio-Fixer\\artifacts\\admin\\src\\pages\\AboutEditor.tsx", "source_location": "L3", "weight": 1.0}, {"source": "d_replit_projects_new_2_portfolio_fixer_artifacts_admin_src_pages_abouteditor_tsx", "target": "lucide_react", "relation": "imports_from", "context": "import", "confidence": "EXTRACTED", "source_file": "D:\\replit_projects\\new_2\\Portfolio-Fixer\\artifacts\\admin\\src\\pages\\AboutEditor.tsx", "source_location": "L4", "weight": 1.0}, {"source": "d_replit_projects_new_2_portfolio_fixer_artifacts_admin_src_pages_abouteditor_tsx", "target": "d_replit_projects_new_2_portfolio_fixer_artifacts_admin_src_lib_api_client_ts", "relation": "imports_from", "context": "import", "confidence": "EXTRACTED", "source_file": "D:\\replit_projects\\new_2\\Portfolio-Fixer\\artifacts\\admin\\src\\pages\\AboutEditor.tsx", "source_location": "L5", "weight": 1.0}, {"source": "d_replit_projects_new_2_portfolio_fixer_artifacts_admin_src_pages_abouteditor_tsx", "target": "lib_api_client_api", "relation": "imports", "context": "import", "confidence": "EXTRACTED", "source_file": "D:\\replit_projects\\new_2\\Portfolio-Fixer\\artifacts\\admin\\src\\pages\\AboutEditor.tsx", "source_location": "L5", "weight": 1.0}, {"source": "d_replit_projects_new_2_portfolio_fixer_artifacts_admin_src_pages_abouteditor_tsx", "target": "d_replit_projects_new_2_portfolio_fixer_artifacts_admin_src_hooks_use_toast_ts", "relation": "imports_from", "context": "import", "confidence": "EXTRACTED", "source_file": "D:\\replit_projects\\new_2\\Portfolio-Fixer\\artifacts\\admin\\src\\pages\\AboutEditor.tsx", "source_location": "L6", "weight": 1.0}, {"source": "d_replit_projects_new_2_portfolio_fixer_artifacts_admin_src_pages_abouteditor_tsx", "target": "hooks_use_toast_usetoast", "relation": "imports", "context": "import", "confidence": "EXTRACTED", "source_file": "D:\\replit_projects\\new_2\\Portfolio-Fixer\\artifacts\\admin\\src\\pages\\AboutEditor.tsx", "source_location": "L6", "weight": 1.0}, {"source": "d_replit_projects_new_2_portfolio_fixer_artifacts_admin_src_pages_abouteditor_tsx", "target": "ui", "relation": "imports_from", "context": "import", "confidence": "EXTRACTED", "source_file": "D:\\replit_projects\\new_2\\Portfolio-Fixer\\artifacts\\admin\\src\\pages\\AboutEditor.tsx", "source_location": "L7", "weight": 1.0}, {"source": "d_replit_projects_new_2_portfolio_fixer_artifacts_admin_src_pages_abouteditor_tsx", "target": "d_replit_projects_new_2_portfolio_fixer_artifacts_admin_src_hooks_usekeyboardshortcuts_ts", "relation": "imports_from", "context": "import", "confidence": "EXTRACTED", "source_file": "D:\\replit_projects\\new_2\\Portfolio-Fixer\\artifacts\\admin\\src\\pages\\AboutEditor.tsx", "source_location": "L8", "weight": 1.0}, {"source": "d_replit_projects_new_2_portfolio_fixer_artifacts_admin_src_pages_abouteditor_tsx", "target": "hooks_usekeyboardshortcuts_usekeyboardshortcuts", "relation": "imports", "context": "import", "confidence": "EXTRACTED", "source_file": "D:\\replit_projects\\new_2\\Portfolio-Fixer\\artifacts\\admin\\src\\pages\\AboutEditor.tsx", "source_location": "L8", "weight": 1.0}, {"source": "d_replit_projects_new_2_portfolio_fixer_artifacts_admin_src_pages_abouteditor_tsx", "target": "d_replit_projects_new_2_portfolio_fixer_artifacts_admin_src_hooks_use_before_unload_ts", "relation": "imports_from", "context": "import", "confidence": "EXTRACTED", "source_file": "D:\\replit_projects\\new_2\\Portfolio-Fixer\\artifacts\\admin\\src\\pages\\AboutEditor.tsx", "source_location": "L9", "weight": 1.0}, {"source": "d_replit_projects_new_2_portfolio_fixer_artifacts_admin_src_pages_abouteditor_tsx", "target": "hooks_use_before_unload_usebeforeunload", "relation": "imports", "context": "import", "confidence": "EXTRACTED", "source_file": "D:\\replit_projects\\new_2\\Portfolio-Fixer\\artifacts\\admin\\src\\pages\\AboutEditor.tsx", "source_location": "L9", "weight": 1.0}, {"source": "d_replit_projects_new_2_portfolio_fixer_artifacts_admin_src_pages_abouteditor_tsx", "target": "pages_abouteditor_aboutformdata", "relation": "contains", "confidence": "EXTRACTED", "source_file": "D:\\replit_projects\\new_2\\Portfolio-Fixer\\artifacts\\admin\\src\\pages\\AboutEditor.tsx", "source_location": "L11", "weight": 1.0}, {"source": "d_replit_projects_new_2_portfolio_fixer_artifacts_admin_src_pages_abouteditor_tsx", "target": "pages_abouteditor_skeletonform", "relation": "contains", "confidence": "EXTRACTED", "source_file": "D:\\replit_projects\\new_2\\Portfolio-Fixer\\artifacts\\admin\\src\\pages\\AboutEditor.tsx", "source_location": "L26", "weight": 1.0}, {"source": "d_replit_projects_new_2_portfolio_fixer_artifacts_admin_src_pages_abouteditor_tsx", "target": "pages_abouteditor_skeletonpreview", "relation": "contains", "confidence": "EXTRACTED", "source_file": "D:\\replit_projects\\new_2\\Portfolio-Fixer\\artifacts\\admin\\src\\pages\\AboutEditor.tsx", "source_location": "L45", "weight": 1.0}, {"source": "d_replit_projects_new_2_portfolio_fixer_artifacts_admin_src_pages_abouteditor_tsx", "target": "pages_abouteditor_getlanguagelabel", "relation": "contains", "confidence": "EXTRACTED", "source_file": "D:\\replit_projects\\new_2\\Portfolio-Fixer\\artifacts\\admin\\src\\pages\\AboutEditor.tsx", "source_location": "L53", "weight": 1.0}, {"source": "d_replit_projects_new_2_portfolio_fixer_artifacts_admin_src_pages_abouteditor_tsx", "target": "pages_abouteditor_livepreviewdata", "relation": "contains", "confidence": "EXTRACTED", "source_file": "D:\\replit_projects\\new_2\\Portfolio-Fixer\\artifacts\\admin\\src\\pages\\AboutEditor.tsx", "source_location": "L61", "weight": 1.0}, {"source": "d_replit_projects_new_2_portfolio_fixer_artifacts_admin_src_pages_abouteditor_tsx", "target": "pages_abouteditor_livepreview", "relation": "contains", "confidence": "EXTRACTED", "source_file": "D:\\replit_projects\\new_2\\Portfolio-Fixer\\artifacts\\admin\\src\\pages\\AboutEditor.tsx", "source_location": "L76", "weight": 1.0}, {"source": "d_replit_projects_new_2_portfolio_fixer_artifacts_admin_src_pages_abouteditor_tsx", "target": "pages_abouteditor_abouteditor", "relation": "contains", "confidence": "EXTRACTED", "source_file": "D:\\replit_projects\\new_2\\Portfolio-Fixer\\artifacts\\admin\\src\\pages\\AboutEditor.tsx", "source_location": "L156", "weight": 1.0}], "raw_calls": [{"caller_nid": "pages_abouteditor_livepreview", "callee": "map", "is_member_call": true, "source_file": "D:\\replit_projects\\new_2\\Portfolio-Fixer\\artifacts\\admin\\src\\pages\\AboutEditor.tsx", "source_location": "L97"}, {"caller_nid": "pages_abouteditor_livepreview", "callee": "map", "is_member_call": true, "source_file": "D:\\replit_projects\\new_2\\Portfolio-Fixer\\artifacts\\admin\\src\\pages\\AboutEditor.tsx", "source_location": "L116"}, {"caller_nid": "pages_abouteditor_livepreview", "callee": "map", "is_member_call": true, "source_file": "D:\\replit_projects\\new_2\\Portfolio-Fixer\\artifacts\\admin\\src\\pages\\AboutEditor.tsx", "source_location": "L141"}, {"caller_nid": "pages_abouteditor_abouteditor", "callee": "useQueryClient", "is_member_call": false, "source_file": "D:\\replit_projects\\new_2\\Portfolio-Fixer\\artifacts\\admin\\src\\pages\\AboutEditor.tsx", "source_location": "L157"}, {"caller_nid": "pages_abouteditor_abouteditor", "callee": "useToast", "is_member_call": false, "source_file": "D:\\replit_projects\\new_2\\Portfolio-Fixer\\artifacts\\admin\\src\\pages\\AboutEditor.tsx", "source_location": "L158"}, {"caller_nid": "pages_abouteditor_abouteditor", "callee": "useQuery", "is_member_call": false, "source_file": "D:\\replit_projects\\new_2\\Portfolio-Fixer\\artifacts\\admin\\src\\pages\\AboutEditor.tsx", "source_location": "L159"}, {"caller_nid": "pages_abouteditor_abouteditor", "callee": "useForm", "is_member_call": false, "source_file": "D:\\replit_projects\\new_2\\Portfolio-Fixer\\artifacts\\admin\\src\\pages\\AboutEditor.tsx", "source_location": "L168"}, {"caller_nid": "pages_abouteditor_abouteditor", "callee": "useFieldArray", "is_member_call": false, "source_file": "D:\\replit_projects\\new_2\\Portfolio-Fixer\\artifacts\\admin\\src\\pages\\AboutEditor.tsx", "source_location": "L177"}, {"caller_nid": "pages_abouteditor_abouteditor", "callee": "useFieldArray", "is_member_call": false, "source_file": "D:\\replit_projects\\new_2\\Portfolio-Fixer\\artifacts\\admin\\src\\pages\\AboutEditor.tsx", "source_location": "L182"}, {"caller_nid": "pages_abouteditor_abouteditor", "callee": "useWatch", "is_member_call": false, "source_file": "D:\\replit_projects\\new_2\\Portfolio-Fixer\\artifacts\\admin\\src\\pages\\AboutEditor.tsx", "source_location": "L187"}, {"caller_nid": "pages_abouteditor_abouteditor", "callee": "useState", "is_member_call": false, "source_file": "D:\\replit_projects\\new_2\\Portfolio-Fixer\\artifacts\\admin\\src\\pages\\AboutEditor.tsx", "source_location": "L188"}, {"caller_nid": "pages_abouteditor_abouteditor", "callee": "useState", "is_member_call": false, "source_file": "D:\\replit_projects\\new_2\\Portfolio-Fixer\\artifacts\\admin\\src\\pages\\AboutEditor.tsx", "source_location": "L189"}, {"caller_nid": "pages_abouteditor_abouteditor", "callee": "useKeyboardShortcuts", "is_member_call": false, "source_file": "D:\\replit_projects\\new_2\\Portfolio-Fixer\\artifacts\\admin\\src\\pages\\AboutEditor.tsx", "source_location": "L191"}, {"caller_nid": "pages_abouteditor_abouteditor", "callee": "useBeforeUnload", "is_member_call": false, "source_file": "D:\\replit_projects\\new_2\\Portfolio-Fixer\\artifacts\\admin\\src\\pages\\AboutEditor.tsx", "source_location": "L194"}, {"caller_nid": "pages_abouteditor_abouteditor", "callee": "useEffect", "is_member_call": false, "source_file": "D:\\replit_projects\\new_2\\Portfolio-Fixer\\artifacts\\admin\\src\\pages\\AboutEditor.tsx", "source_location": "L196"}, {"caller_nid": "pages_abouteditor_abouteditor", "callee": "useMutation", "is_member_call": false, "source_file": "D:\\replit_projects\\new_2\\Portfolio-Fixer\\artifacts\\admin\\src\\pages\\AboutEditor.tsx", "source_location": "L207"}, {"caller_nid": "pages_abouteditor_abouteditor", "callee": "handleSubmit", "is_member_call": false, "source_file": "D:\\replit_projects\\new_2\\Portfolio-Fixer\\artifacts\\admin\\src\\pages\\AboutEditor.tsx", "source_location": "L289"}, {"caller_nid": "pages_abouteditor_abouteditor", "callee": "register", "is_member_call": false, "source_file": "D:\\replit_projects\\new_2\\Portfolio-Fixer\\artifacts\\admin\\src\\pages\\AboutEditor.tsx", "source_location": "L303"}, {"caller_nid": "pages_abouteditor_abouteditor", "callee": "map", "is_member_call": true, "source_file": "D:\\replit_projects\\new_2\\Portfolio-Fixer\\artifacts\\admin\\src\\pages\\AboutEditor.tsx", "source_location": "L329"}, {"caller_nid": "pages_abouteditor_abouteditor", "callee": "map", "is_member_call": true, "source_file": "D:\\replit_projects\\new_2\\Portfolio-Fixer\\artifacts\\admin\\src\\pages\\AboutEditor.tsx", "source_location": "L390"}, {"caller_nid": "pages_abouteditor_abouteditor", "callee": "map", "is_member_call": true, "source_file": "D:\\replit_projects\\new_2\\Portfolio-Fixer\\artifacts\\admin\\src\\pages\\AboutEditor.tsx", "source_location": "L443"}]}